uuid0/__init__.py
uuid0/core.py
uuid0/django.py
uuid0-0.2.7.dist-info/DESCRIPTION.rst
uuid0-0.2.7.dist-info/LICENSE.txt
uuid0-0.2.7.dist-info/METADATA
uuid0-0.2.7.dist-info/RECORD
uuid0-0.2.7.dist-info/WHEEL
uuid0-0.2.7.dist-info/metadata.json
uuid0-0.2.7.dist-info/top_level.txt
