Metadata-Version: 1.1
Name: uuid0
Version: 0.2.7
Summary: A library to make better timestamped UUIDs for databases and web apps
Home-page: https://github.com/oaclaf/uuid0
Author: oaclaf
Author-email: oaclafm@gmail.com
License: MIT
Platform: UNKNOWN
Classifier: Development Status :: 3 - Alpha
Classifier: Intended Audience :: Developers
Classifier: Natural Language :: English
Classifier: License :: OSI Approved :: MIT License
Classifier: Operating System :: OS Independent
Classifier: Programming Language :: Python
Classifier: Programming Language :: Python :: 3
Classifier: Programming Language :: Python :: 3.5
Classifier: Programming Language :: Python :: 3.6
Classifier: Framework :: Django
Classifier: Topic :: Software Development :: Libraries :: Python Modules
